sphinxcontrib/sphinx_pandera/__init__.py
sphinxcontrib/sphinx_pandera/directives.py
sphinxcontrib/sphinx_pandera/documenters.py
sphinxcontrib/sphinx_pandera/py.typed
sphinx_pandera-0.0.5.dist-info/LICENSE
sphinx_pandera-0.0.5.dist-info/METADATA
sphinx_pandera-0.0.5.dist-info/WHEEL
sphinx_pandera-0.0.5.dist-info/entry_points.txt
sphinx_pandera-0.0.5.dist-info/RECORD
