Metadata-Version: 2.1
Name: sphinx-pandera
Version: 0.0.5
Summary: Sphinx Pandera
Home-page: https://gitlab.has-sante.fr/has-sante/public/alpha/sphinx-pandera
License: EUPL-v1.2
Author: Timothée Chehab
Author-email: t.chehab@has-sante.fr
Requires-Python: >=3.11,<4.0
Classifier: Intended Audience :: Developers
Classifier: License :: Other/Proprietary License
Classifier: Natural Language :: English
Classifier: Operating System :: OS Independent
Classifier: Programming Language :: Python
Classifier: Programming Language :: Python :: 3
Classifier: Programming Language :: Python :: 3.11
Classifier: Programming Language :: Python :: 3.12
Classifier: Programming Language :: Python :: Implementation :: CPython
Classifier: Topic :: Software Development :: Libraries :: Python Modules
Requires-Dist: pandera (>=0,<1)
Requires-Dist: sphinx (>=7)
Project-URL: Repository, https://gitlab.has-sante.fr/has-sante/public/alpha/sphinx-pandera
